hiddenAlphabet/__init__.py
hiddenAlphabet/hiddenAlphabet.py
hiddenAlphabet-0.0.9.dist-info/METADATA
hiddenAlphabet-0.0.9.dist-info/WHEEL
hiddenAlphabet-0.0.9.dist-info/license.txt
hiddenAlphabet-0.0.9.dist-info/top_level.txt
hiddenAlphabet-0.0.9.dist-info/RECORD
