Metadata-Version: 2.1
Name: hiddenAlphabet
Version: 0.0.9
Summary: Early testing.
Home-page: https://github.com/pypa/sampleproject
Author: Mac Scheffer, Donaldo Celaj
Author-email: author@example.com
License: UNKNOWN
Platform: UNKNOWN
Classifier: Programming Language :: Python :: 3.6
Classifier: License :: OSI Approved :: MIT License
Classifier: Operating System :: OS Independent
